pyembeds/__init__.py
pyembeds/data/MyRestaurant_AD_Reviews.txt
pyembeds/data/__init__.py
pyembeds/data/load_data.py
pyembeds/data/manzoni_1.txt
pyembeds/data/negative-words.txt
pyembeds/data/positive-words.txt
pyembeds/data/stopwords_italian.txt
pyembeds/testing/__init__.py
pyembeds/testing/auto_testing.py
pyembeds/vis/__init__.py
pyembeds/vis/utils.py
pyembeds_sssa-0.0.7.dist-info/LICENSE
pyembeds_sssa-0.0.7.dist-info/METADATA
pyembeds_sssa-0.0.7.dist-info/WHEEL
pyembeds_sssa-0.0.7.dist-info/top_level.txt
pyembeds_sssa-0.0.7.dist-info/RECORD
