Metadata-Version: 2.1
Name: pyembeds-sssa
Version: 0.0.7
Summary: A small package for Introduction to Programming and Machine Learning Course
Home-page: https://github.com/EMbeDS-education
Author: Daniele Licari e Andrea Vandin
Author-email: daniele.licari@gmail.com
Project-URL: Bug Tracker, https://github.com/EMbeDS-education/issues
Classifier: Programming Language :: Python :: 3
Classifier: License :: OSI Approved :: MIT License
Classifier: Operating System :: OS Independent
Requires-Python: >=3.7
License-File: LICENSE
